MANIFEST.in
README.rst
jsonlogging.py
setup.py
json_logging_py.egg-info/PKG-INFO
json_logging_py.egg-info/SOURCES.txt
json_logging_py.egg-info/dependency_links.txt
json_logging_py.egg-info/pbr.json
json_logging_py.egg-info/top_level.txt