Metadata-Version: 1.1
Name: json-logging-py
Version: 0.2
Summary: JSON / Logstash formatters for Python logging
Home-page: https://github.com/sebest/json-logging-py
Author: Sebastien Estienne
Author-email: rs@dailymotion.com
License: MIT
Keywords: json,logging,logstash
Platform: UNKNOWN
Classifier: Development Status :: 4 - Beta
Classifier: Intended Audience :: Developers
Classifier: License :: OSI Approved :: MIT License
Classifier: Natural Language :: English
Classifier: Operating System :: Unix
Classifier: Programming Language :: Python :: 2.7
Classifier: Programming Language :: Python :: 3
Classifier: Programming Language :: Python :: 3.4
Classifier: Operating System :: OS Independent
